sentinel_sdk/__init__.py
sentinel_sdk/sdk.py
sentinel_sdk/types.py
sentinel_sdk/utils.py
sentinel_sdk/modules/__init__.py
sentinel_sdk/modules/deposit.py
sentinel_sdk/modules/lease.py
sentinel_sdk/modules/node.py
sentinel_sdk/modules/plan.py
sentinel_sdk/modules/provider.py
sentinel_sdk/modules/session.py
sentinel_sdk/modules/subscription.py
sentinel_sdk/modules/swap.py
sentinel_sdk/modules/wireguard.py
sentinel_sdk/querier/querier.py
sentinel_sdk/transactor/transactor.py
sentinel_sdk-0.1.1.dist-info/METADATA
sentinel_sdk-0.1.1.dist-info/WHEEL
sentinel_sdk-0.1.1.dist-info/licenses/LICENSE
sentinel_sdk-0.1.1.dist-info/RECORD
