Metadata-Version: 2.4
Name: sentinel_sdk
Version: 0.1.1
Summary: A Sentinel SDK Written in Python
Author: NAST0R
Author-email: Tkd-Alex <alex.tkd.alex@gmail.com>, MathNodes <freQniK@mathnodes.com'>
License: GPL-3.0 license
License-File: LICENSE
Keywords: cosmos,dvpn,mospy,protobuf,sentinel,sentinel_protobuf,sentinel_sdk
Classifier: Development Status :: 3 - Alpha
Classifier: License :: OSI Approved :: GNU General Public License v3 (GPLv3)
Classifier: Operating System :: OS Independent
Classifier: Programming Language :: Python :: 3
Requires-Python: >=3.10
Requires-Dist: bip-utils==2.9.0
Requires-Dist: grpcio>=1.51.1
Requires-Dist: mospy-wallet==0.6.0
Requires-Dist: sentinel-protobuf==0.5.1
